{"accounts":[{"account":{"active":true,"allocationHistory":[{"allocationId":"l4b5vj5SeDqw7TZhANvtpQ","credTimestampMs":1653782400000,"grainReceipt":{"amount":"3005284438549101568","id":"MKi6wla5Q0tmlo4ho5P9nw"}},{"allocationId":"VR1zPCrFvDLB1gpYOcRpPQ","credTimestampMs":1654387200000,"grainReceipt":{"amount":"3005284478225907712","id":"MKi6wla5Q0tmlo4ho5P9nw"}},{"allocationId":"lbq0EFWrQZZOPCjawGW1Pw","credTimestampMs":1654992000000,"grainReceipt":{"amount":"3005284586495150592","id":"MKi6wla5Q0tmlo4ho5P9nw"}},{"allocationId":"gnat2cNTVcR3CNrbnGE5sA","credTimestampMs":1655596800000,"grainReceipt":{"amount":"2937162226970543616","id":"MKi6wla5Q0tmlo4ho5P9nw"}},{"allocationId":"gc2DG8zwX6Wl2CeDkZnN5g","credTimestampMs":1656201600000,"grainReceipt":{"amount":"2271914062362386176","id":"MKi6wla5Q0tmlo4ho5P9nw"}}],"balance":"14224929792603089664","identity":{"address":"N\u0000sourcecred\u0000core\u0000IDENTITY\u0000MKi6wla5Q0tmlo4ho5P9nw\u0000","aliases":[{"address":"N\u0000sourcecred\u0000discord\u0000MEMBER\u0000user\u0000949326778919452712\u0000","description":"discord/JohnMark13#4398"},{"address":"N\u0000sourcecred\u0000discord\u0000MEMBER\u0000user\u0000907282205347295302\u0000","description":"discord/JohnMark13#0838"},{"address":"N\u0000sourcecred\u0000core\u0000IDENTITY\u0000BafmXsPGLiORzK7GFN1cXA\u0000","description":"identity @JohnMark13-discord (id: BafmXsPGLiORzK7GFN1cXA)"},{"address":"N\u0000sourcecred\u0000github\u0000USERLIKE\u0000USER\u0000johnmark13\u0000","description":"github/[@johnmark13](https://github.com/johnmark13)"},{"address":"N\u0000sourcecred\u0000core\u0000IDENTITY\u0000IY3mt3vO9SVXT5eS52z3AA\u0000","description":"identity @johnmark13-github (id: IY3mt3vO9SVXT5eS52z3AA)"}],"id":"MKi6wla5Q0tmlo4ho5P9nw","name":"JohnMark13","subtype":"USER"},"mergedIdentityIds":["MKi6wla5Q0tmlo4ho5P9nw","BafmXsPGLiORzK7GFN1cXA","IY3mt3vO9SVXT5eS52z3AA"],"paid":"14224929792603089664","payoutAddresses":{}},"cred":[0.04459493493924699,0.40135427920520894,3.9689492779400974,20.425014372063185,9.713998194404175,10.063713188771217,1.1181904042008168],"totalCred":45.735814651523945},{"account":{"active":false,"allocationHistory":[],"balance":"0","identity":{"address":"N\u0000sourcecred\u0000core\u0000IDENTITY\u0000eyMFM3JyeP1nyy6S9O2EaA\u0000","aliases":[{"address":"N\u0000sourcecred\u0000discord\u0000MEMBER\u0000bot\u0000983351896926470165\u0000","description":"discord/Foundance-SourceCred-Bot#0939"}],"id":"eyMFM3JyeP1nyy6S9O2EaA","name":"Foundance-SourceCred-Bot","subtype":"BOT"},"mergedIdentityIds":["eyMFM3JyeP1nyy6S9O2EaA"],"paid":"0","payoutAddresses":{}},"cred":[5.5647248013884197e-64,5.5647248013884197e-64,5.5647248013884197e-64,5.5647248013884197e-64,5.5647248013884197e-64,5.5647248013884197e-64,5.5647248013884197e-64],"totalCred":3.8953073609718934e-63},{"account":{"active":false,"allocationHistory":[],"balance":"0","identity":{"address":"N\u0000sourcecred\u0000core\u0000IDENTITY\u0000KUQUxRebjznndVFPIyxmeA\u0000","aliases":[{"address":"N\u0000sourcecred\u0000github\u0000USERLIKE\u0000BOT\u0000dependabot\u0000","description":"github/[@dependabot](https://github.com/apps/dependabot)"}],"id":"KUQUxRebjznndVFPIyxmeA","name":"dependabot","subtype":"BOT"},"mergedIdentityIds":["KUQUxRebjznndVFPIyxmeA"],"paid":"0","payoutAddresses":{}},"cred":[0.17580974507253894,1.5822875489867063,15.647065890791954,1.590026868587305,0.2532029313018998,0.9420022850734857,0.10466692222656744],"totalCred":20.295062192040454},{"account":{"active":false,"allocationHistory":[],"balance":"0","identity":{"address":"N\u0000sourcecred\u0000core\u0000IDENTITY\u000019VZMZKe0XjjZLOJLW7pKw\u0000","aliases":[{"address":"N\u0000sourcecred\u0000discord\u0000MEMBER\u0000bot\u0000512333785338216465\u0000","description":"discord/Captcha-bot#3928"}],"id":"19VZMZKe0XjjZLOJLW7pKw","name":"Captcha-bot","subtype":"BOT"},"mergedIdentityIds":["19VZMZKe0XjjZLOJLW7pKw"],"paid":"0","payoutAddresses":{}},"cred":[5.5647248013884197e-64,5.5647248013884197e-64,5.5647248013884197e-64,5.5647248013884197e-64,5.5647248013884197e-64,5.5647248013884197e-64,5.5647248013884197e-64],"totalCred":3.8953073609718934e-63},{"account":{"active":true,"allocationHistory":[{"allocationId":"l4b5vj5SeDqw7TZhANvtpQ","credTimestampMs":1653782400000,"grainReceipt":{"amount":"664713124583598592","id":"kjdd5fDjSycKqyGAU9ZbAQ"}},{"allocationId":"VR1zPCrFvDLB1gpYOcRpPQ","credTimestampMs":1654387200000,"grainReceipt":{"amount":"664713006300838016","id":"kjdd5fDjSycKqyGAU9ZbAQ"}},{"allocationId":"lbq0EFWrQZZOPCjawGW1Pw","credTimestampMs":1654992000000,"grainReceipt":{"amount":"664712991286706176","id":"kjdd5fDjSycKqyGAU9ZbAQ"}},{"allocationId":"gnat2cNTVcR3CNrbnGE5sA","credTimestampMs":1655596800000,"grainReceipt":{"amount":"570309547907286272","id":"kjdd5fDjSycKqyGAU9ZbAQ"}},{"allocationId":"gc2DG8zwX6Wl2CeDkZnN5g","credTimestampMs":1656201600000,"grainReceipt":{"amount":"0","id":"kjdd5fDjSycKqyGAU9ZbAQ"}}],"balance":"2564448670078429056","identity":{"address":"N\u0000sourcecred\u0000core\u0000IDENTITY\u0000kjdd5fDjSycKqyGAU9ZbAQ\u0000","aliases":[{"address":"N\u0000sourcecred\u0000discord\u0000MEMBER\u0000user\u0000883468767756185660\u0000","description":"discord/sfsf#8492"}],"id":"kjdd5fDjSycKqyGAU9ZbAQ","name":"Sara","subtype":"USER"},"mergedIdentityIds":["kjdd5fDjSycKqyGAU9ZbAQ"],"paid":"2564448670078429056","payoutAddresses":{}},"cred":[0.010315991537644816,0.09284380925692472,0.9181232672830076,3.5986875407177843,0.7313546649135486,1.2955247167678,0.14394719777747012],"totalCred":6.79079718825418},{"account":{"active":true,"allocationHistory":[{"allocationId":"l4b5vj5SeDqw7TZhANvtpQ","credTimestampMs":1653782400000,"grainReceipt":{"amount":"806201635808251648","id":"uDKw3VLL5i0E4BTRWDtLIw"}},{"allocationId":"VR1zPCrFvDLB1gpYOcRpPQ","credTimestampMs":1654387200000,"grainReceipt":{"amount":"806201635048663168","id":"uDKw3VLL5i0E4BTRWDtLIw"}},{"allocationId":"lbq0EFWrQZZOPCjawGW1Pw","credTimestampMs":1654992000000,"grainReceipt":{"amount":"806201590709449600","id":"uDKw3VLL5i0E4BTRWDtLIw"}},{"allocationId":"gnat2cNTVcR3CNrbnGE5sA","credTimestampMs":1655596800000,"grainReceipt":{"amount":"978771760509997312","id":"uDKw3VLL5i0E4BTRWDtLIw"}},{"allocationId":"gc2DG8zwX6Wl2CeDkZnN5g","credTimestampMs":1656201600000,"grainReceipt":{"amount":"645517497602798592","id":"uDKw3VLL5i0E4BTRWDtLIw"}}],"balance":"4042894119679160320","identity":{"address":"N\u0000sourcecred\u0000core\u0000IDENTITY\u0000uDKw3VLL5i0E4BTRWDtLIw\u0000","aliases":[{"address":"N\u0000sourcecred\u0000discord\u0000MEMBER\u0000user\u0000888498914205007955\u0000","description":"discord/Shailesh-Ubhrani#9964"}],"id":"uDKw3VLL5i0E4BTRWDtLIw","name":"Shailesh","subtype":"USER"},"mergedIdentityIds":["uDKw3VLL5i0E4BTRWDtLIw"],"paid":"4042894119679160320","payoutAddresses":{}},"cred":[0.033713765056045335,0.30342361631714393,3.000525201571266,7.938465390891294,1.316023659636854,3.5663019096447544,0.396255792498791],"totalCred":16.55470933561615},{"account":{"active":false,"allocationHistory":[],"balance":"0","identity":{"address":"N\u0000sourcecred\u0000core\u0000IDENTITY\u0000HZLWVxH7OVBhRgpVdeooZQ\u0000","aliases":[{"address":"N\u0000sourcecred\u0000discord\u0000MEMBER\u0000bot\u0000914215932405096459\u0000","description":"discord/Dework#9886"}],"id":"HZLWVxH7OVBhRgpVdeooZQ","name":"Dework","subtype":"BOT"},"mergedIdentityIds":["HZLWVxH7OVBhRgpVdeooZQ"],"paid":"0","payoutAddresses":{}},"cred":[0.01078217183653947,0.09703956028214616,0.9596132398840673,0.09694065261518175,0.009793094954593068,0.0009903132279482725,0.00011003478295853585],"totalCred":1.1752690675834345},{"account":{"active":true,"allocationHistory":[{"allocationId":"l4b5vj5SeDqw7TZhANvtpQ","credTimestampMs":1653782400000,"grainReceipt":{"amount":"523800801059048192","id":"dgjrW2bS80QAx6fwmoTDyg"}},{"allocationId":"VR1zPCrFvDLB1gpYOcRpPQ","credTimestampMs":1654387200000,"grainReceipt":{"amount":"523800880424591104","id":"dgjrW2bS80QAx6fwmoTDyg"}},{"allocationId":"lbq0EFWrQZZOPCjawGW1Pw","credTimestampMs":1654992000000,"grainReceipt":{"amount":"523800831508693440","id":"dgjrW2bS80QAx6fwmoTDyg"}},{"allocationId":"gnat2cNTVcR3CNrbnGE5sA","credTimestampMs":1655596800000,"grainReceipt":{"amount":"513756464612172800","id":"dgjrW2bS80QAx6fwmoTDyg"}},{"allocationId":"gc2DG8zwX6Wl2CeDkZnN5g","credTimestampMs":1656201600000,"grainReceipt":{"amount":"2082568440034815232","id":"dgjrW2bS80QAx6fwmoTDyg"}}],"balance":"4167727417639320768","identity":{"address":"N\u0000sourcecred\u0000core\u0000IDENTITY\u0000dgjrW2bS80QAx6fwmoTDyg\u0000","aliases":[{"address":"N\u0000sourcecred\u0000discord\u0000MEMBER\u0000user\u0000910804162047008789\u0000","description":"discord/Artiom#2445"}],"id":"dgjrW2bS80QAx6fwmoTDyg","name":"Artiom","subtype":"USER"},"mergedIdentityIds":["dgjrW2bS80QAx6fwmoTDyg"],"paid":"4167727417639320768","payoutAddresses":{}},"cred":[0.02846225908805468,0.2561604185837747,2.5331410421098606,4.493404502943583,6.98802479464049,5.196007218136008,0.5773341700459315],"totalCred":20.0725344055477},{"account":{"active":false,"allocationHistory":[],"balance":"0","identity":{"address":"N\u0000sourcecred\u0000core\u0000IDENTITY\u0000gP0qm2R6r7PABLSL74pCYw\u0000","aliases":[{"address":"N\u0000sourcecred\u0000discord\u0000MEMBER\u0000bot\u0000983709360343625760\u0000","description":"discord/Foundance-Project-Bot#8759"}],"id":"gP0qm2R6r7PABLSL74pCYw","name":"Foundance-Project-Bot","subtype":"BOT"},"mergedIdentityIds":["gP0qm2R6r7PABLSL74pCYw"],"paid":"0","payoutAddresses":{}},"cred":[5.5647248013884197e-64,5.5647248013884197e-64,5.5647248013884197e-64,5.5647248013884197e-64,5.5647248013884197e-64,5.5647248013884197e-64,5.5647248013884197e-64],"totalCred":3.8953073609718934e-63},{"account":{"active":true,"allocationHistory":[{"allocationId":"l4b5vj5SeDqw7TZhANvtpQ","credTimestampMs":1653782400000,"grainReceipt":{"amount":"0","id":"hYRYhZYCpr3RTEbr1TQ1HQ"}},{"allocationId":"VR1zPCrFvDLB1gpYOcRpPQ","credTimestampMs":1654387200000,"grainReceipt":{"amount":"0","id":"hYRYhZYCpr3RTEbr1TQ1HQ"}},{"allocationId":"lbq0EFWrQZZOPCjawGW1Pw","credTimestampMs":1654992000000,"grainReceipt":{"amount":"192","id":"hYRYhZYCpr3RTEbr1TQ1HQ"}},{"allocationId":"gnat2cNTVcR3CNrbnGE5sA","credTimestampMs":1655596800000,"grainReceipt":{"amount":"0","id":"hYRYhZYCpr3RTEbr1TQ1HQ"}},{"allocationId":"gc2DG8zwX6Wl2CeDkZnN5g","credTimestampMs":1656201600000,"grainReceipt":{"amount":"0","id":"hYRYhZYCpr3RTEbr1TQ1HQ"}}],"balance":"192","identity":{"address":"N\u0000sourcecred\u0000core\u0000IDENTITY\u0000hYRYhZYCpr3RTEbr1TQ1HQ\u0000","aliases":[{"address":"N\u0000sourcecred\u0000discord\u0000MEMBER\u0000user\u0000264471900313485312\u0000","description":"discord/Burhan#8049"}],"id":"hYRYhZYCpr3RTEbr1TQ1HQ","name":"Burhan","subtype":"USER"},"mergedIdentityIds":["hYRYhZYCpr3RTEbr1TQ1HQ"],"paid":"192","payoutAddresses":{}},"cred":[0.0000033661856086234403,0.000030295667003154986,0.00029959048688171005,0.002965608941159762,0.029356499145535876,0.29059936310817774,0.03228882025471435],"totalCred":0.3555435437890812},{"account":{"active":false,"allocationHistory":[],"balance":"0","identity":{"address":"N\u0000sourcecred\u0000core\u0000IDENTITY\u00005foN6cJNevo2kT69ekmsng\u0000","aliases":[{"address":"N\u0000sourcecred\u0000discord\u0000MEMBER\u0000user\u0000697354932667285525\u0000","description":"discord/ChristianSauer#7030"}],"id":"5foN6cJNevo2kT69ekmsng","name":"ChristianSauer","subtype":"USER"},"mergedIdentityIds":["5foN6cJNevo2kT69ekmsng"],"paid":"0","payoutAddresses":{}},"cred":[0.0022719758522917197,0.02044767537433478,0.2022059536947568,0.02042683393063397,0.0020635630135551817,0.00020867335630647772,0.000023186085623169692],"totalCred":0.24764786130750208},{"account":{"active":false,"allocationHistory":[],"balance":"0","identity":{"address":"N\u0000sourcecred\u0000core\u0000IDENTITY\u0000N8N3YFrDEyaToebXQG4SyA\u0000","aliases":[{"address":"N\u0000sourcecred\u0000discord\u0000MEMBER\u0000user\u0000938026339594809355\u0000","description":"discord/Andreea-Dinu#6141"}],"id":"N8N3YFrDEyaToebXQG4SyA","name":"Andreea-Dinu","subtype":"USER"},"mergedIdentityIds":["N8N3YFrDEyaToebXQG4SyA"],"paid":"0","payoutAddresses":{}},"cred":[0.0022733242290444433,0.02045981076521943,0.20232595921450064,0.0215956940571951,0.01363215785753754,0.11472576340220458,0.012747307108186374],"totalCred":0.38776001663388815},{"account":{"active":false,"allocationHistory":[],"balance":"0","identity":{"address":"N\u0000sourcecred\u0000core\u0000IDENTITY\u0000t3V2ym1ED12HZAHG4K0gHA\u0000","aliases":[{"address":"N\u0000sourcecred\u0000github\u0000USERLIKE\u0000BOT\u0000github-actions\u0000","description":"github/[@github-actions](https://github.com/apps/github-actions)"}],"id":"t3V2ym1ED12HZAHG4K0gHA","name":"github-actions","subtype":"BOT"},"mergedIdentityIds":["t3V2ym1ED12HZAHG4K0gHA"],"paid":"0","payoutAddresses":{}},"cred":[0.0014864970258584604,0.013378472673657122,0.13229821659997712,1.3096036666595547,3.4053234785987323,3.4034867873445642,1.4632597206515827],"totalCred":9.728836839553928},{"account":{"active":false,"allocationHistory":[],"balance":"0","identity":{"address":"N\u0000sourcecred\u0000core\u0000IDENTITY\u0000GPJfO2JoqIXRZ4nwqaXnGQ\u0000","aliases":[{"address":"N\u0000sourcecred\u0000github\u0000USERLIKE\u0000BOT\u0000credbot\u0000","description":"github/[@credbot](https://github.com/credbot)"}],"id":"GPJfO2JoqIXRZ4nwqaXnGQ","name":"credbot","subtype":"BOT"},"mergedIdentityIds":["GPJfO2JoqIXRZ4nwqaXnGQ"],"paid":"0","payoutAddresses":{}},"cred":[0.00003321094798372113,0.0002988985043704487,0.002955774120962313,0.02925884063687703,0.2896326344259379,0.2899895281670796,0.03222105867479928],"totalCred":0.6443899454780103},{"account":{"active":false,"allocationHistory":[],"balance":"0","identity":{"address":"N\u0000sourcecred\u0000core\u0000IDENTITY\u0000JeRs7Z0uwzPXsMEyHBMYEA\u0000","aliases":[{"address":"N\u0000sourcecred\u0000discord\u0000MEMBER\u0000user\u0000786991579621359626\u0000","description":"discord/Mariano#7030"}],"id":"JeRs7Z0uwzPXsMEyHBMYEA","name":"Mariano","subtype":"USER"},"mergedIdentityIds":["JeRs7Z0uwzPXsMEyHBMYEA"],"paid":"0","payoutAddresses":{}},"cred":[0.000388262003024694,0.0034943577770781033,0.03455531332982394,0.34205875970962174,3.38603210487757,3.655773031523215,0.40619703305862426],"totalCred":7.828498862278957},{"account":{"active":false,"allocationHistory":[],"balance":"0","identity":{"address":"N\u0000sourcecred\u0000core\u0000IDENTITY\u0000R97jmmrAyIW3WhG3YLNfxA\u0000","aliases":[{"address":"N\u0000sourcecred\u0000discord\u0000MEMBER\u0000user\u0000377189195594203138\u0000","description":"discord/dilkROM#8860"}],"id":"R97jmmrAyIW3WhG3YLNfxA","name":"dilkROM","subtype":"USER"},"mergedIdentityIds":["R97jmmrAyIW3WhG3YLNfxA"],"paid":"0","payoutAddresses":{}},"cred":[0.0022726627552019183,0.020453857500579885,0.20226708804797885,0.021022285772972372,0.007956946622314448,0.058547058471547286,0.006505228830120279],"totalCred":0.3190251280007151},{"account":{"active":false,"allocationHistory":[],"balance":"0","identity":{"address":"N\u0000sourcecred\u0000core\u0000IDENTITY\u0000Gd6dZc0xkJT1Aoz2l5C3ag\u0000","aliases":[{"address":"N\u0000sourcecred\u0000discord\u0000MEMBER\u0000user\u0000390538447560900618\u0000","description":"discord/BenjaminDrury#3295"}],"id":"Gd6dZc0xkJT1Aoz2l5C3ag","name":"BenjaminDrury","subtype":"USER"},"mergedIdentityIds":["Gd6dZc0xkJT1Aoz2l5C3ag"],"paid":"0","payoutAddresses":{}},"cred":[0.000005222511261539752,0.00004700259799243294,0.00046480345506144134,0.004601031718517231,0.045545512753217506,0.4508540785401574,0.05009489964154049],"totalCred":0.551612551217748}],"intervals":[{"endTimeMs":1653782400000,"startTimeMs":1653177600000},{"endTimeMs":1654387200000,"startTimeMs":1653782400000},{"endTimeMs":1654992000000,"startTimeMs":1654387200000},{"endTimeMs":1655596800000,"startTimeMs":1654992000000},{"endTimeMs":1656201600000,"startTimeMs":1655596800000},{"endTimeMs":1656806400000,"startTimeMs":1656201600000},{"endTimeMs":1657411200000,"startTimeMs":1656806400000}],"unclaimedAliases":[]}